Metadata-Version: 2.1
Name: vllm-rocm
Version: 0.6.3
Summary: A high-throughput and memory-efficient inference and serving engine for LLMs with AMD GPU support
Home-page: https://github.com/vllm-project/vllm
Author: vLLM Team
License: Apache 2.0
Project-URL: Homepage, https://github.com/vllm-project/vllm
Project-URL: Documentation, https://vllm.readthedocs.io/en/latest/
Classifier: Programming Language :: Python :: 3.8
Classifier: Programming Language :: Python :: 3.9
Classifier: Programming Language :: Python :: 3.10
Classifier: Programming Language :: Python :: 3.11
Classifier: Programming Language :: Python :: 3.12
Classifier: License :: OSI Approved :: Apache Software License
Classifier: Intended Audience :: Developers
Classifier: Intended Audience :: Information Technology
Classifier: Intended Audience :: Science/Research
Classifier: Topic :: Scientific/Engineering :: Artificial Intelligence
Classifier: Topic :: Scientific/Engineering :: Information Analysis
Requires-Python: >=3.8
License-File: LICENSE
Requires-Dist: psutil
Requires-Dist: sentencepiece
Requires-Dist: numpy<2.0.0
Requires-Dist: requests>=2.26.0
Requires-Dist: tqdm
Requires-Dist: py-cpuinfo
Requires-Dist: transformers>=4.45.0
Requires-Dist: tokenizers>=0.19.1
Requires-Dist: protobuf
Requires-Dist: aiohttp
Requires-Dist: openai>=1.40.0
Requires-Dist: uvicorn[standard]
Requires-Dist: pydantic>=2.9
Requires-Dist: pillow
Requires-Dist: prometheus-client>=0.18.0
Requires-Dist: prometheus-fastapi-instrumentator>=7.0.0
Requires-Dist: tiktoken>=0.6.0
Requires-Dist: lm-format-enforcer==0.10.6
Requires-Dist: outlines<0.1,>=0.0.43
Requires-Dist: typing-extensions>=4.10
Requires-Dist: filelock>=3.10.4
Requires-Dist: partial-json-parser
Requires-Dist: pyzmq
Requires-Dist: msgspec
Requires-Dist: gguf==0.10.0
Requires-Dist: importlib-metadata
Requires-Dist: mistral-common[opencv]>=1.4.4
Requires-Dist: pyyaml
Requires-Dist: einops
Requires-Dist: awscli
Requires-Dist: boto3
Requires-Dist: botocore
Requires-Dist: ray>=2.10.0
Requires-Dist: peft
Requires-Dist: pytest-asyncio
Requires-Dist: tensorizer>=2.9.0
Requires-Dist: fastapi<0.113.0,>=0.107.0; python_version < "3.9"
Requires-Dist: six>=1.16.0; python_version > "3.11"
Requires-Dist: setuptools>=74.1.1; python_version > "3.11"
Requires-Dist: fastapi!=0.113.*,!=0.114.0,>=0.107.0; python_version >= "3.9"
Provides-Extra: audio
Requires-Dist: librosa; extra == "audio"
Requires-Dist: soundfile; extra == "audio"
Provides-Extra: tensorizer
Requires-Dist: tensorizer>=2.9.0; extra == "tensorizer"
